btsmp/__init__.py
btsmp/central.py
btsmp/peripheral.py
btsmp/sm.py
btsmp/smp.py
btsmp/pytransform/__init__.py
btsmp/pytransform/platforms/linux/aarch64/_pytransform.so
btsmp/pytransform/platforms/linux/x86_64/_pytransform.so
btsmp-0.0.11.dist-info/LICENSE.txt
btsmp-0.0.11.dist-info/METADATA
btsmp-0.0.11.dist-info/WHEEL
btsmp-0.0.11.dist-info/top_level.txt
btsmp-0.0.11.dist-info/RECORD
