Metadata-Version: 2.1
Name: btsmp
Version: 0.0.11
Summary: Bluetooth SMP Utilities
Home-page: https://pypi.org/project/btsmp
Author: Cibo
Author-email: cibo@bio-electric.com
License: Proprietary
Platform: UNKNOWN
Classifier: Operating System :: POSIX :: Linux
Classifier: Programming Language :: Python :: 3
Classifier: Programming Language :: Python :: 3 :: Only
Classifier: Programming Language :: Python :: 3.10
Classifier: License :: Other/Proprietary License
Requires-Python: ==3.10.*
License-File: LICENSE.txt
Requires-Dist: bthci (>=0.0.33)
Requires-Dist: pyclui (>=0.0.17)
Requires-Dist: scapy (>=2.4.5)
